odoo/addons/agreement_mrp/README.rst
odoo/addons/agreement_mrp/__init__.py
odoo/addons/agreement_mrp/__manifest__.py
odoo/addons/agreement_mrp/i18n/agreement_mrp.pot
odoo/addons/agreement_mrp/i18n/de.po
odoo/addons/agreement_mrp/i18n/es.po
odoo/addons/agreement_mrp/i18n/fr.po
odoo/addons/agreement_mrp/i18n/it.po
odoo/addons/agreement_mrp/i18n/pt.po
odoo/addons/agreement_mrp/i18n/pt_BR.po
odoo/addons/agreement_mrp/i18n/zh_CN.po
odoo/addons/agreement_mrp/models/__init__.py
odoo/addons/agreement_mrp/models/agreement.py
odoo/addons/agreement_mrp/models/mrp.py
odoo/addons/agreement_mrp/readme/CONTRIBUTORS.rst
odoo/addons/agreement_mrp/readme/CREDITS.rst
odoo/addons/agreement_mrp/readme/DESCRIPTION.rst
odoo/addons/agreement_mrp/readme/ROADMAP.rst
odoo/addons/agreement_mrp/readme/USAGE.rst
odoo/addons/agreement_mrp/static/description/icon.png
odoo/addons/agreement_mrp/static/description/index.html
odoo/addons/agreement_mrp/views/agreement_view.xml
odoo/addons/agreement_mrp/views/mrp_view.xml
odoo12_addon_agreement_mrp-12.0.1.0.1.dist-info/METADATA
odoo12_addon_agreement_mrp-12.0.1.0.1.dist-info/WHEEL
odoo12_addon_agreement_mrp-12.0.1.0.1.dist-info/top_level.txt
odoo12_addon_agreement_mrp-12.0.1.0.1.dist-info/RECORD
